{"\\\\bravo\\Media\\Movies\\21 (2008)\\21 (2008).mkv":{"path":"\\\\bravo\\Media\\Movies\\21 (2008)\\21 (2008).mkv","isProcessed":false},"\\\\bravo\\Media\\Movies\\A Bad Moms Christmas (2017)\\A Bad Moms Christmas (2017).mkv":{"path":"\\\\bravo\\Media\\Movies\\A Bad Moms Christmas (2017)\\A Bad Moms Christmas (2017).mkv","isProcessed":false},"\\\\bravo\\Media\\Movies\\A Quiet Place (2018)\\A Quiet Place (2018).mkv":{"path":"\\\\bravo\\Media\\Movies\\A Quiet Place (2018)\\A Quiet Place (2018).mkv","isProcessed":false},"\\\\bravo\\Media\\Movies\\Allied (2016)\\Allied (2016).mkv":{"path":"\\\\bravo\\Media\\Movies\\Allied (2016)\\Allied (2016).mkv","isProcessed":false},"\\\\bravo\\Media\\Movies\\Avengers Infinity War (2018)\\Avengers Infinity War (2018).mkv":{"path":"\\\\bravo\\Media\\Movies\\Avengers Infinity War (2018)\\Avengers Infinity War (2018).mkv","isProcessed":false},"\\\\bravo\\Media\\Movies\\Baywatch (2017)\\Baywatch (2017).mkv":{"path":"\\\\bravo\\Media\\Movies\\Baywatch (2017)\\Baywatch (2017).mkv","isProcessed":false},"\\\\bravo\\Media\\Movies\\Black Panther (2018)\\Black Panther (2018).mkv":{"path":"\\\\bravo\\Media\\Movies\\Black Panther (2018)\\Black Panther (2018).mkv","isProcessed":false},"\\\\bravo\\Media\\Movies\\Bright (2017)\\Bright (2017).mkv":{"path":"\\\\bravo\\Media\\Movies\\Bright (2017)\\Bright (2017).mkv","isProcessed":false},"\\\\bravo\\Media\\Movies\\Cabin Fever (2016)\\Cabin Fever (2016).mkv":{"path":"\\\\bravo\\Media\\Movies\\Cabin Fever (2016)\\Cabin Fever (2016).mkv","isProcessed":false},"\\\\bravo\\Media\\Movies\\Cabin.Fever.2002.1080p.BluRay.x264-Japhson\\japhson-cf-sample.mkv":{"path":"\\\\bravo\\Media\\Movies\\Cabin.Fever.2002.1080p.BluRay.x264-Japhson\\japhson-cf-sample.mkv","isProcessed":false},"\\\\bravo\\Media\\Movies\\Captain America Civil War (2016)\\Captain America Civil War (2016).mkv":{"path":"\\\\bravo\\Media\\Movies\\Captain America Civil War (2016)\\Captain America Civil War (2016).mkv","isProcessed":false},"\\\\bravo\\Media\\Movies\\Cargo (2018)\\Cargo (2017).mkv":{"path":"\\\\bravo\\Media\\Movies\\Cargo (2018)\\Cargo (2017).mkv","isProcessed":false},"\\\\bravo\\Media\\Movies\\Casino Royale (2006)\\Casino Royale (2006).mkv":{"path":"\\\\bravo\\Media\\Movies\\Casino Royale (2006)\\Casino Royale (2006).mkv","isProcessed":false},"\\\\bravo\\Media\\Movies\\Cinderella Man (2005)\\Cinderella Man (2005).mkv":{"path":"\\\\bravo\\Media\\Movies\\Cinderella Man (2005)\\Cinderella Man (2005).mkv","isProcessed":false},"\\\\bravo\\Media\\Movies\\Coco.2017.DVDScr.XVID.AC3.HQ.Hive-CM8\\C0c0.2o17.DVDScr.sample.avi":{"path":"\\\\bravo\\Media\\Movies\\Coco.2017.DVDScr.XVID.AC3.HQ.Hive-CM8\\C0c0.2o17.DVDScr.sample.avi","isProcessed":false},"\\\\bravo\\Media\\Movies\\Darkest Hour (2017)\\Darkest Hour (2017).mkv":{"path":"\\\\bravo\\Media\\Movies\\Darkest Hour (2017)\\Darkest Hour (2017).mkv","isProcessed":false},"\\\\bravo\\Media\\Movies\\Deadpool (2016)\\Deadpool (2016).mkv":{"path":"\\\\bravo\\Media\\Movies\\Deadpool (2016)\\Deadpool (2016).mkv","isProcessed":false},"\\\\bravo\\Media\\Movies\\Deadpool 2 (2018)\\Deadpool 2 (2018).mkv":{"path":"\\\\bravo\\Media\\Movies\\Deadpool 2 (2018)\\Deadpool 2 (2018).mkv","isProcessed":false},"\\\\bravo\\Media\\Movies\\Death Note (2017)\\Death Note (2017).mkv":{"path":"\\\\bravo\\Media\\Movies\\Death Note (2017)\\Death Note (2017).mkv","isProcessed":false},"\\\\bravo\\Media\\Movies\\Die Hard (1988)\\Die Hard (1988).mkv":{"path":"\\\\bravo\\Media\\Movies\\Die Hard (1988)\\Die Hard (1988).mkv","isProcessed":false},"\\\\bravo\\Media\\Movies\\Downsizing (2017)\\Downsizing (2017).mkv":{"path":"\\\\bravo\\Media\\Movies\\Downsizing (2017)\\Downsizing (2017).mkv","isProcessed":false},"\\\\bravo\\Media\\Movies\\Drop Dead Gorgeous (1999)\\Drop Dead Gorgeous (1999).avi":{"path":"\\\\bravo\\Media\\Movies\\Drop Dead Gorgeous (1999)\\Drop Dead Gorgeous (1999).avi","isProcessed":false},"\\\\bravo\\Media\\Movies\\Edge of Tomorrow (2014)\\Edge of Tomorrow (2014).mkv":{"path":"\\\\bravo\\Media\\Movies\\Edge of Tomorrow (2014)\\Edge of Tomorrow (2014).mkv","isProcessed":false},"\\\\bravo\\Media\\Movies\\Focus (2015)\\Focus (2015).mkv":{"path":"\\\\bravo\\Media\\Movies\\Focus (2015)\\Focus (2015).mkv","isProcessed":false},"\\\\bravo\\Media\\Movies\\Friends with Benefits (2011)\\Friends with Benefits (2011).mkv":{"path":"\\\\bravo\\Media\\Movies\\Friends with Benefits (2011)\\Friends with Benefits (2011).mkv","isProcessed":false},"\\\\bravo\\Media\\Movies\\Guardians of the Galaxy Vol. 2 (2017)\\Guardians of the Galaxy Vol. 2 (2017).mkv":{"path":"\\\\bravo\\Media\\Movies\\Guardians of the Galaxy Vol. 2 (2017)\\Guardians of the Galaxy Vol. 2 (2017).mkv","isProcessed":false},"\\\\bravo\\Media\\Movies\\How to Lose a Guy in 10 Days (2003)\\How to Lose a Guy in 10 Days (2003).mkv":{"path":"\\\\bravo\\Media\\Movies\\How to Lose a Guy in 10 Days (2003)\\How to Lose a Guy in 10 Days (2003).mkv","isProcessed":false},"\\\\bravo\\Media\\Movies\\I, Robot (2004)\\I, Robot (2004).mkv":{"path":"\\\\bravo\\Media\\Movies\\I, Robot (2004)\\I, Robot (2004).mkv","isProcessed":false},"\\\\bravo\\Media\\Movies\\I, Tonya (2017)\\I, Tonya (2017).mkv":{"path":"\\\\bravo\\Media\\Movies\\I, Tonya (2017)\\I, Tonya (2017).mkv","isProcessed":false},"\\\\bravo\\Media\\Movies\\Iron Man (2008)\\Iron Man (2008).mkv":{"path":"\\\\bravo\\Media\\Movies\\Iron Man (2008)\\Iron Man (2008).mkv","isProcessed":false},"\\\\bravo\\Media\\Movies\\Iron Man 3 (2013)\\Iron Man 3 (2013).mkv":{"path":"\\\\bravo\\Media\\Movies\\Iron Man 3 (2013)\\Iron Man 3 (2013).mkv","isProcessed":false},"\\\\bravo\\Media\\Movies\\Jack Reacher (2012)\\Jack Reacher (2012).mkv":{"path":"\\\\bravo\\Media\\Movies\\Jack Reacher (2012)\\Jack Reacher (2012).mkv","isProcessed":false},"\\\\bravo\\Media\\Movies\\Jumanji (1995)\\Jumanji (1995).mkv":{"path":"\\\\bravo\\Media\\Movies\\Jumanji (1995)\\Jumanji (1995).mkv","isProcessed":false},"\\\\bravo\\Media\\Movies\\Jumanji Welcome to the Jungle (2017)\\Jumanji Welcome to the Jungle (2017).mkv":{"path":"\\\\bravo\\Media\\Movies\\Jumanji Welcome to the Jungle (2017)\\Jumanji Welcome to the Jungle (2017).mkv","isProcessed":false},"\\\\bravo\\Media\\Movies\\Justice League (2017)\\Justice League (2017).mkv":{"path":"\\\\bravo\\Media\\Movies\\Justice League (2017)\\Justice League (2017).mkv","isProcessed":false},"\\\\bravo\\Media\\Movies\\King Arthur Legend of the Sword (2017)\\King Arthur Legend of the Sword (2017).mkv":{"path":"\\\\bravo\\Media\\Movies\\King Arthur Legend of the Sword (2017)\\King Arthur Legend of the Sword (2017).mkv","isProcessed":false},"\\\\bravo\\Media\\Movies\\Knight and Day (2010)\\Knight and Day (2010).mkv":{"path":"\\\\bravo\\Media\\Movies\\Knight and Day (2010)\\Knight and Day (2010).mkv","isProcessed":false},"\\\\bravo\\Media\\Movies\\Lady Bird (2017)\\Lady Bird (2017).mkv":{"path":"\\\\bravo\\Media\\Movies\\Lady Bird (2017)\\Lady Bird (2017).mkv","isProcessed":false},"\\\\bravo\\Media\\Movies\\Love Actually (2003)\\Love Actually (2003).mkv":{"path":"\\\\bravo\\Media\\Movies\\Love Actually (2003)\\Love Actually (2003).mkv","isProcessed":false},"\\\\bravo\\Media\\Movies\\Mad Max Fury Road (2015)\\Mad Max Fury Road (2015).mkv":{"path":"\\\\bravo\\Media\\Movies\\Mad Max Fury Road (2015)\\Mad Max Fury Road (2015).mkv","isProcessed":false},"\\\\bravo\\Media\\Movies\\Mission Impossible (1996)\\Mission Impossible (1996).mkv":{"path":"\\\\bravo\\Media\\Movies\\Mission Impossible (1996)\\Mission Impossible (1996).mkv","isProcessed":false},"\\\\bravo\\Media\\Movies\\Molly's Game (2017)\\Molly's Game (2017).mkv":{"path":"\\\\bravo\\Media\\Movies\\Molly's Game (2017)\\Molly's Game (2017).mkv","isProcessed":false},"\\\\bravo\\Media\\Movies\\Moulin Rouge! (2001)\\Moulin Rouge! (2001).mkv":{"path":"\\\\bravo\\Media\\Movies\\Moulin Rouge! (2001)\\Moulin Rouge! (2001).mkv","isProcessed":false},"\\\\bravo\\Media\\Movies\\My Little Pony Equestria Girls - Rainbow Rocks (2014)\\My Little Pony Equestria Girls - Rainbow Rocks (2014).mkv":{"path":"\\\\bravo\\Media\\Movies\\My Little Pony Equestria Girls - Rainbow Rocks (2014)\\My Little Pony Equestria Girls - Rainbow Rocks (2014).mkv","isProcessed":false},"\\\\bravo\\Media\\Movies\\National Treasure (2004)\\National Treasure (2004).mkv":{"path":"\\\\bravo\\Media\\Movies\\National Treasure (2004)\\National Treasure (2004).mkv","isProcessed":false},"\\\\bravo\\Media\\Movies\\National Treasure Book of Secrets (2007)\\National Treasure Book of Secrets (2007).mkv":{"path":"\\\\bravo\\Media\\Movies\\National Treasure Book of Secrets (2007)\\National Treasure Book of Secrets (2007).mkv","isProcessed":false},"\\\\bravo\\Media\\Movies\\No Country for Old Men (2007)\\No Country for Old Men (2007).mkv":{"path":"\\\\bravo\\Media\\Movies\\No Country for Old Men (2007)\\No Country for Old Men (2007).mkv","isProcessed":false},"\\\\bravo\\Media\\Movies\\Ocean's Eleven (2001)\\Ocean's Eleven (2001).mkv":{"path":"\\\\bravo\\Media\\Movies\\Ocean's Eleven (2001)\\Ocean's Eleven (2001).mkv","isProcessed":false},"\\\\bravo\\Media\\Movies\\Pacific Rim Uprising (2018)\\Pacific Rim Uprising (2018).mkv":{"path":"\\\\bravo\\Media\\Movies\\Pacific Rim Uprising (2018)\\Pacific Rim Uprising (2018).mkv","isProcessed":false},"\\\\bravo\\Media\\Movies\\Planes, Trains and Automobiles (1987)\\Planes, Trains and Automobiles (1987).mkv":{"path":"\\\\bravo\\Media\\Movies\\Planes, Trains and Automobiles (1987)\\Planes, Trains and Automobiles (1987).mkv","isProcessed":false},"\\\\bravo\\Media\\Movies\\Quantum of Solace (2008)\\Quantum of Solace (2008).mkv":{"path":"\\\\bravo\\Media\\Movies\\Quantum of Solace (2008)\\Quantum of Solace (2008).mkv","isProcessed":false},"\\\\bravo\\Media\\Movies\\Rampage (2018)\\Rampage (2018).mkv":{"path":"\\\\bravo\\Media\\Movies\\Rampage (2018)\\Rampage (2018).mkv","isProcessed":false},"\\\\bravo\\Media\\Movies\\Role Models (2008)\\Role Models (2008).mkv":{"path":"\\\\bravo\\Media\\Movies\\Role Models (2008)\\Role Models (2008).mkv","isProcessed":false},"\\\\bravo\\Media\\Movies\\Romeo + Juliet (1996)\\Romeo + Juliet (1996).mkv":{"path":"\\\\bravo\\Media\\Movies\\Romeo + Juliet (1996)\\Romeo + Juliet (1996).mkv","isProcessed":false},"\\\\bravo\\Media\\Movies\\Shallow Hal (2001)\\Shallow Hal (2001).mkv":{"path":"\\\\bravo\\Media\\Movies\\Shallow Hal (2001)\\Shallow Hal (2001).mkv","isProcessed":false},"\\\\bravo\\Media\\Movies\\Skyfall (2012)\\Skyfall (2012).mkv":{"path":"\\\\bravo\\Media\\Movies\\Skyfall (2012)\\Skyfall (2012).mkv","isProcessed":false},"\\\\bravo\\Media\\Movies\\Snitch (2013)\\Snitch (2013).mkv":{"path":"\\\\bravo\\Media\\Movies\\Snitch (2013)\\Snitch (2013).mkv","isProcessed":false},"\\\\bravo\\Media\\Movies\\Spider-Man Homecoming (2017)\\Spider-Man Homecoming (2017).mkv":{"path":"\\\\bravo\\Media\\Movies\\Spider-Man Homecoming (2017)\\Spider-Man Homecoming (2017).mkv","isProcessed":false},"\\\\bravo\\Media\\Movies\\Splice (2009)\\Splice (2009).mkv":{"path":"\\\\bravo\\Media\\Movies\\Splice (2009)\\Splice (2009).mkv","isProcessed":false},"\\\\bravo\\Media\\Movies\\Star Wars Episode I - The Phantom Menace (1999)\\Star Wars Episode I - The Phantom Menace (1999).mkv":{"path":"\\\\bravo\\Media\\Movies\\Star Wars Episode I - The Phantom Menace (1999)\\Star Wars Episode I - The Phantom Menace (1999).mkv","isProcessed":false},"\\\\bravo\\Media\\Movies\\Star Wars The Force Awakens (2015)\\Star Wars The Force Awakens (2015).mkv":{"path":"\\\\bravo\\Media\\Movies\\Star Wars The Force Awakens (2015)\\Star Wars The Force Awakens (2015).mkv","isProcessed":false},"\\\\bravo\\Media\\Movies\\Straight Outta Compton (2015)\\Straight Outta Compton (2015).mkv":{"path":"\\\\bravo\\Media\\Movies\\Straight Outta Compton (2015)\\Straight Outta Compton (2015).mkv","isProcessed":false},"\\\\bravo\\Media\\Movies\\Straight.Outta.Compton.2015.DC.PROPER.MULTI.1080p.BluRay.x264-AiRLiNE\\air-stouco1080-sample.mkv":{"path":"\\\\bravo\\Media\\Movies\\Straight.Outta.Compton.2015.DC.PROPER.MULTI.1080p.BluRay.x264-AiRLiNE\\air-stouco1080-sample.mkv","isProcessed":false},"\\\\bravo\\Media\\Movies\\Swing.State.2017.1080p.AMZN.WEB-DL.DDP5.1.H.264-monkee\\3GOhMa7CDAmxUybEOueiGr8ffXzzCV9v.mkv":{"path":"\\\\bravo\\Media\\Movies\\Swing.State.2017.1080p.AMZN.WEB-DL.DDP5.1.H.264-monkee\\3GOhMa7CDAmxUybEOueiGr8ffXzzCV9v.mkv","isProcessed":false},"\\\\bravo\\Media\\Movies\\Swing.State.2017.1080p.AMZN.WEB-DL.DDP5.1.H.264-monkee.1\\Swing.State.2017.1080p.AMZN.WEB-DL.DDP5.1.H.264-monkee.mkv":{"path":"\\\\bravo\\Media\\Movies\\Swing.State.2017.1080p.AMZN.WEB-DL.DDP5.1.H.264-monkee.1\\Swing.State.2017.1080p.AMZN.WEB-DL.DDP5.1.H.264-monkee.mkv","isProcessed":false},"\\\\bravo\\Media\\Movies\\Table 19 (2017)\\Table 19 (2017).mkv":{"path":"\\\\bravo\\Media\\Movies\\Table 19 (2017)\\Table 19 (2017).mkv","isProcessed":false},"\\\\bravo\\Media\\Movies\\Taken (2008)\\Taken (2008).mkv":{"path":"\\\\bravo\\Media\\Movies\\Taken (2008)\\Taken (2008).mkv","isProcessed":false},"\\\\bravo\\Media\\Movies\\Terminator 2 Judgment Day (1991)\\Terminator 2 Judgment Day (1991).mkv":{"path":"\\\\bravo\\Media\\Movies\\Terminator 2 Judgment Day (1991)\\Terminator 2 Judgment Day (1991).mkv","isProcessed":false},"\\\\bravo\\Media\\Movies\\Terminator Genisys (2015)\\Terminator Genisys (2015).mkv":{"path":"\\\\bravo\\Media\\Movies\\Terminator Genisys (2015)\\Terminator Genisys (2015).mkv","isProcessed":false},"\\\\bravo\\Media\\Movies\\The Campaign (2012)\\The Campaign (2012).mkv":{"path":"\\\\bravo\\Media\\Movies\\The Campaign (2012)\\The Campaign (2012).mkv","isProcessed":false},"\\\\bravo\\Media\\Movies\\The Greatest Showman (2017)\\The Greatest Showman (2017).mkv":{"path":"\\\\bravo\\Media\\Movies\\The Greatest Showman (2017)\\The Greatest Showman (2017).mkv","isProcessed":false},"\\\\bravo\\Media\\Movies\\The Lord of the Rings The Return of the King (2003)\\The Lord of the Rings The Return of the King (2003).mkv":{"path":"\\\\bravo\\Media\\Movies\\The Lord of the Rings The Return of the King (2003)\\The Lord of the Rings The Return of the King (2003).mkv","isProcessed":false},"\\\\bravo\\Media\\Movies\\The Nice Guys (2016)\\The Nice Guys (2016).mkv":{"path":"\\\\bravo\\Media\\Movies\\The Nice Guys (2016)\\The Nice Guys (2016).mkv","isProcessed":false},"\\\\bravo\\Media\\Movies\\The Phantom of the Opera (2004)\\The Phantom of the Opera (2004).mkv":{"path":"\\\\bravo\\Media\\Movies\\The Phantom of the Opera (2004)\\The Phantom of the Opera (2004).mkv","isProcessed":false},"\\\\bravo\\Media\\Movies\\The Post (2017)\\The Post (2017).mkv":{"path":"\\\\bravo\\Media\\Movies\\The Post (2017)\\The Post (2017).mkv","isProcessed":false},"\\\\bravo\\Media\\Movies\\The Siege (1998)\\The Siege (1998).mkv":{"path":"\\\\bravo\\Media\\Movies\\The Siege (1998)\\The Siege (1998).mkv","isProcessed":false},"\\\\bravo\\Media\\Movies\\The Terminator (1984)\\The Terminator (1984).mkv":{"path":"\\\\bravo\\Media\\Movies\\The Terminator (1984)\\The Terminator (1984).mkv","isProcessed":false},"\\\\bravo\\Media\\Movies\\The.Incredibles.2004.1080p.BluRay.x264-EbP\\Boundin.1080p.BluRay.x264-EbP.mkv":{"path":"\\\\bravo\\Media\\Movies\\The.Incredibles.2004.1080p.BluRay.x264-EbP\\Boundin.1080p.BluRay.x264-EbP.mkv","isProcessed":false},"\\\\bravo\\Media\\Movies\\The.Incredibles.2004.1080p.BluRay.x264-EbP\\Jack.Jack.Attack.1080p.BluRay.x264-EbP.mkv":{"path":"\\\\bravo\\Media\\Movies\\The.Incredibles.2004.1080p.BluRay.x264-EbP\\Jack.Jack.Attack.1080p.BluRay.x264-EbP.mkv","isProcessed":false},"\\\\bravo\\Media\\Movies\\The.Nut.Job.2014.1080p.BluRay.x264-AQOS\\aqos-tnj-1080p-sample.mkv":{"path":"\\\\bravo\\Media\\Movies\\The.Nut.Job.2014.1080p.BluRay.x264-AQOS\\aqos-tnj-1080p-sample.mkv","isProcessed":false},"\\\\bravo\\Media\\Movies\\This Is the End (2013)\\This Is the End (2013).mkv":{"path":"\\\\bravo\\Media\\Movies\\This Is the End (2013)\\This Is the End (2013).mkv","isProcessed":false},"\\\\bravo\\Media\\Movies\\Thor Ragnarok (2017)\\Thor Ragnarok (2017).mkv":{"path":"\\\\bravo\\Media\\Movies\\Thor Ragnarok (2017)\\Thor Ragnarok (2017).mkv","isProcessed":false},"\\\\bravo\\Media\\Movies\\Training Day (2001)\\Training Day (2001).mkv":{"path":"\\\\bravo\\Media\\Movies\\Training Day (2001)\\Training Day (2001).mkv","isProcessed":false},"\\\\bravo\\Media\\Movies\\V for Vendetta (2006)\\V for Vendetta (2005).mkv":{"path":"\\\\bravo\\Media\\Movies\\V for Vendetta (2006)\\V for Vendetta (2005).mkv","isProcessed":false},"\\\\bravo\\Media\\Movies\\Valerian and the City of a Thousand Planets (2017)\\Valerian and the City of a Thousand Planets (2017).mkv":{"path":"\\\\bravo\\Media\\Movies\\Valerian and the City of a Thousand Planets (2017)\\Valerian and the City of a Thousand Planets (2017).mkv","isProcessed":false},"\\\\bravo\\Media\\Movies\\Waiting. (2005)\\Waiting. (2005).mkv":{"path":"\\\\bravo\\Media\\Movies\\Waiting. (2005)\\Waiting. (2005).mkv","isProcessed":false},"\\\\bravo\\Media\\Movies\\Warrior (2011)\\Warrior (2011).mkv":{"path":"\\\\bravo\\Media\\Movies\\Warrior (2011)\\Warrior (2011).mkv","isProcessed":false},"\\\\bravo\\Media\\Movies\\Watchmen (2009)\\Watchmen (2009).mkv":{"path":"\\\\bravo\\Media\\Movies\\Watchmen (2009)\\Watchmen (2009).mkv","isProcessed":false},"\\\\bravo\\Media\\Movies\\What We Do in the Shadows (2014)\\What We Do in the Shadows (2014).mkv":{"path":"\\\\bravo\\Media\\Movies\\What We Do in the Shadows (2014)\\What We Do in the Shadows (2014).mkv","isProcessed":false},"\\\\bravo\\Media\\Movies\\Whiplash (2014)\\Whiplash (2014).mkv":{"path":"\\\\bravo\\Media\\Movies\\Whiplash (2014)\\Whiplash (2014).mkv","isProcessed":false},"\\\\bravo\\Media\\Movies\\Wild Wild West (1999)\\Wild Wild West (1999).mkv":{"path":"\\\\bravo\\Media\\Movies\\Wild Wild West (1999)\\Wild Wild West (1999).mkv","isProcessed":false},"\\\\bravo\\Media\\Movies\\Wind River (2017)\\Wind River (2017).mkv":{"path":"\\\\bravo\\Media\\Movies\\Wind River (2017)\\Wind River (2017).mkv","isProcessed":false},"\\\\bravo\\Media\\Movies\\World War Z (2013)\\World War Z (2013).mkv":{"path":"\\\\bravo\\Media\\Movies\\World War Z (2013)\\World War Z (2013).mkv","isProcessed":false}}